logging_k8s_metadata/__init__.py
logging_k8s_metadata/formatters.py
logging_k8s_metadata/utils.py
logging_k8s_metadata/tests/__init__.py
logging_k8s_metadata/tests/test_logging.py
logging_k8s_metadata-1.0.3.dist-info/METADATA
logging_k8s_metadata-1.0.3.dist-info/WHEEL
logging_k8s_metadata-1.0.3.dist-info/top_level.txt
logging_k8s_metadata-1.0.3.dist-info/RECORD
