Metadata-Version: 2.1
Name: logging-k8s-metadata
Version: 1.0.3
Summary: logging-k8s-metadata
Author: Niyaz Batyrshin
Author-email: Niyaz.Batyrshin@gmail.com
License: UNKNOWN
Platform: UNKNOWN
Classifier: Intended Audience :: Developers
Classifier: Operating System :: OS Independent
Classifier: Programming Language :: Python
Classifier: Programming Language :: Python :: 3
Classifier: Programming Language :: Python :: 3.6
Classifier: Programming Language :: Python :: 3.7
Classifier: Programming Language :: Python :: 3.8
Classifier: Programming Language :: Python :: 3.9
Classifier: Programming Language :: Python :: 3.10
Classifier: Topic :: Software Development :: Libraries :: Python Modules
Provides-Extra: fluentd
Requires-Dist: fluent-logger ; extra == 'fluentd'
